setup.py
remotelib/__init__.py
remotelib/exceptions.py
remotelib/host.py
remotelib/policy.py
remotelib/result.py
remotelib/script.py
remotelib.egg-info/PKG-INFO
remotelib.egg-info/SOURCES.txt
remotelib.egg-info/dependency_links.txt
remotelib.egg-info/requires.txt
remotelib.egg-info/top_level.txt