Metadata-Version: 1.0
Name: remotelib
Version: 1.0.0
Summary: Remotelib
Home-page: https://google.com
Author: Martin Klapproth
Author-email: martin.klapproth@googlemail.com
License: GPL
Platform: UNKNOWN
